MANIFEST.in
README.txt
setup.py
cs/__init__.py
cs.htmlmailer.egg-info/PKG-INFO
cs.htmlmailer.egg-info/SOURCES.txt
cs.htmlmailer.egg-info/dependency_links.txt
cs.htmlmailer.egg-info/namespace_packages.txt
cs.htmlmailer.egg-info/not-zip-safe
cs.htmlmailer.egg-info/requires.txt
cs.htmlmailer.egg-info/top_level.txt
cs/htmlmailer/__init__.py
cs/htmlmailer/mailer.py
docs/HISTORY.txt