Metadata-Version: 2.1
Name: cs.htmlmailer
Version: 2.1
Summary: A library to send emails with HTML and Text mixed content
Home-page: https://github.com/codesyntax/cs.htmlmailer/
Author: Mikel Larreategi
Author-email: mlarreategi@codesyntax.com
License: GPL
Classifier: Development Status :: 5 - Production/Stable
Classifier: Intended Audience :: Developers
Classifier: Operating System :: OS Independent
Classifier: Programming Language :: Python
Classifier: Topic :: Software Development :: Libraries :: Python Modules
